resilient_sdk/LICENSE
resilient_sdk/__init__.py
resilient_sdk/app.py
resilient_sdk/cmds/__init__.py
resilient_sdk/cmds/base_cmd.py
resilient_sdk/cmds/clone.py
resilient_sdk/cmds/codegen.py
resilient_sdk/cmds/dev.py
resilient_sdk/cmds/docgen.py
resilient_sdk/cmds/extract.py
resilient_sdk/cmds/list.py
resilient_sdk/cmds/run_init.py
resilient_sdk/cmds/validate.py
resilient_sdk/cmds/ext/__init__.py
resilient_sdk/cmds/ext/ext_package.py
resilient_sdk/data/codegen/templates/package_template/Dockerfile.jinja2
resilient_sdk/data/codegen/templates/package_template/MANIFEST.in.jinja2
resilient_sdk/data/codegen/templates/package_template/README.md.jinja2
resilient_sdk/data/codegen/templates/package_template/apikey_permissions.txt.jinja2
resilient_sdk/data/codegen/templates/package_template/setup.py.jinja2
resilient_sdk/data/codegen/templates/package_template/tox.ini.jinja2
resilient_sdk/data/codegen/templates/package_template/data/playbook.md.jinja2
resilient_sdk/data/codegen/templates/package_template/data/workflow.md.jinja2
resilient_sdk/data/codegen/templates/package_template/doc/screenshots/main.png
resilient_sdk/data/codegen/templates/package_template/package/LICENSE.jinja2
resilient_sdk/data/codegen/templates/package_template/package/__init__.py.jinja2
resilient_sdk/data/codegen/templates/package_template/package/components/__init__.py.jinja2
resilient_sdk/data/codegen/templates/package_template/package/components/atomic_function.py.jinja2
resilient_sdk/data/codegen/templates/package_template/package/lib/__init__.py.jinja2
resilient_sdk/data/codegen/templates/package_template/package/lib/app_common.py.jinja2
resilient_sdk/data/codegen/templates/package_template/package/poller/__init__.py.jinja2
resilient_sdk/data/codegen/templates/package_template/package/poller/poller.py.jinja2
resilient_sdk/data/codegen/templates/package_template/package/poller/data/soar_close_case.jinja2
resilient_sdk/data/codegen/templates/package_template/package/poller/data/soar_create_case.jinja2
resilient_sdk-51.0.7.2.16540.dist-info/METADATA
resilient_sdk-51.0.7.2.16540.dist-info/WHEEL
resilient_sdk-51.0.7.2.16540.dist-info/entry_points.txt
resilient_sdk-51.0.7.2.16540.dist-info/top_level.txt
resilient_sdk-51.0.7.2.16540.dist-info/RECORD
