Metadata-Version: 2.1
Name: resilient_sdk
Version: 51.0.7.2.16540
Summary: Python SDK for developing Apps for IBM SOAR
Home-page: https://github.com/ibmresilient/resilient-python-api/tree/main/resilient-sdk
Author: IBM SOAR
License: MIT
Project-URL: Documentation, https://ibm.biz/soar-python-docs
Project-URL: IBM Community, https://ibm.biz/soarcommunity
Project-URL: Change Log, https://ibm.biz/resilient-sdk-changes
Keywords: ibm,soar,resilient,resilient-circuits,circuits,resilient-sdk,sdk
Classifier: Programming Language :: Python :: 3.9
Classifier: Programming Language :: Python :: 3.11
Classifier: Programming Language :: Python :: 3.12
Requires-Python: >=3.9
Requires-Dist: resilient >=51.0.7.2
Requires-Dist: genson ~=1.3
Requires-Dist: packaging ~=25.0
Requires-Dist: jinja2 ~=3.1
